PythonZiranyuyanChuliDierBan20170304/README.md
PythonZiranyuyanChuliDierBan20170304/__init__.py
PythonZiranyuyanChuliDierBan20170304/__main__.py
PythonZiranyuyanChuliDierBan20170304/file.epub
PythonZiranyuyanChuliDierBan20170304/index.html
PythonZiranyuyanChuliDierBan20170304/css/__init__.py
PythonZiranyuyanChuliDierBan20170304/css/annotations.css
PythonZiranyuyanChuliDierBan20170304/css/main.css
PythonZiranyuyanChuliDierBan20170304/css/normalize.css
PythonZiranyuyanChuliDierBan20170304/css/popup.css
PythonZiranyuyanChuliDierBan20170304/font/__init__.py
PythonZiranyuyanChuliDierBan20170304/font/fontello.eot
PythonZiranyuyanChuliDierBan20170304/font/fontello.svg
PythonZiranyuyanChuliDierBan20170304/font/fontello.ttf
PythonZiranyuyanChuliDierBan20170304/font/fontello.woff
PythonZiranyuyanChuliDierBan20170304/img/__init__.py
PythonZiranyuyanChuliDierBan20170304/img/annotator-glyph-sprite.png
PythonZiranyuyanChuliDierBan20170304/img/annotator-icon-sprite.png
PythonZiranyuyanChuliDierBan20170304/img/apple-touch-icon.png
PythonZiranyuyanChuliDierBan20170304/img/cancelfullscreen.png
PythonZiranyuyanChuliDierBan20170304/img/close.png
PythonZiranyuyanChuliDierBan20170304/img/fullscreen.png
PythonZiranyuyanChuliDierBan20170304/img/loader.gif
PythonZiranyuyanChuliDierBan20170304/img/menu-icon.png
PythonZiranyuyanChuliDierBan20170304/img/save.png
PythonZiranyuyanChuliDierBan20170304/img/saved.png
PythonZiranyuyanChuliDierBan20170304/img/settings-s.png
PythonZiranyuyanChuliDierBan20170304/img/settings.png
PythonZiranyuyanChuliDierBan20170304/img/star.png
PythonZiranyuyanChuliDierBan20170304/js/__init__.py
PythonZiranyuyanChuliDierBan20170304/js/epub.js
PythonZiranyuyanChuliDierBan20170304/js/epub.min.js
PythonZiranyuyanChuliDierBan20170304/js/epub.min.map
PythonZiranyuyanChuliDierBan20170304/js/hooks.min.js
PythonZiranyuyanChuliDierBan20170304/js/hooks.min.map
PythonZiranyuyanChuliDierBan20170304/js/reader.js
PythonZiranyuyanChuliDierBan20170304/js/reader.js.map
python_ziranyuyan_chuli_dier_ban_20170304-2024.3.2.0.dist-info/METADATA
python_ziranyuyan_chuli_dier_ban_20170304-2024.3.2.0.dist-info/WHEEL
python_ziranyuyan_chuli_dier_ban_20170304-2024.3.2.0.dist-info/entry_points.txt
python_ziranyuyan_chuli_dier_ban_20170304-2024.3.2.0.dist-info/top_level.txt
python_ziranyuyan_chuli_dier_ban_20170304-2024.3.2.0.dist-info/RECORD
